PyVisualFields/__init__.py
PyVisualFields/utils.py
PyVisualFields/vfprogression.py
PyVisualFields/visualFields.py
PyVisualFields-1.0.4.dist-info/METADATA
PyVisualFields-1.0.4.dist-info/WHEEL
PyVisualFields-1.0.4.dist-info/license
PyVisualFields-1.0.4.dist-info/top_level.txt
PyVisualFields-1.0.4.dist-info/RECORD
