Metadata-Version: 2.1
Name: PyVisualFields
Version: 1.0.4
Summary: A python toolkit for visual field analysis
Home-page: https://github.com/mohaEs/PyVisualField
Author: Mohammad Eslami
Author-email: Mohammad_eslami@meei.harvard.edu
Project-URL: Bug Tracker, https://github.com/mohaEs/PyVisualField/issues
Project-URL: Demo Normalization, https://github.com/mohaEs/PyVisualField/blob/main/demo_2_Deviation_Analysis.ipynb
Project-URL: Demo Plotting, https://github.com/mohaEs/PyVisualField/blob/main/demo_3_Plotting.ipynb
Project-URL: Demo Analysis, https://github.com/mohaEs/PyVisualField/blob/main/demo_4_Analysis.ipynb
Project-URL: Demo Data, https://github.com/mohaEs/PyVisualField/blob/main/demo_1_Data.ipynb
Project-URL: Harvard Ophthalmology AI LAB, https://ophai.hms.harvard.edu/
Classifier: Programming Language :: Python :: 3
Classifier: License :: OSI Approved :: MIT License
Classifier: Operating System :: OS Independent
Requires-Python: >=3.6
License-File: license
Requires-Dist: tzlocal (>=3.0)
Requires-Dist: scikit-image (>=0.18.1)
Requires-Dist: pandas (>=1.2.4)
Requires-Dist: PyPDF2 (>=1.26.0)
Requires-Dist: PyMuPDF (>=1.19.1)
Requires-Dist: reportlab (>=3.6.2)
Requires-Dist: matplotlib (>=3.3.4)
